datavolley/__init__.py
datavolley/get_players_from_md.py
datavolley/helpers.py
datavolley/pycourt.py
datavolley/read_dv.py
pydatavolley-2.2.9.dist-info/METADATA
pydatavolley-2.2.9.dist-info/WHEEL
pydatavolley-2.2.9.dist-info/entry_points.txt
pydatavolley-2.2.9.dist-info/top_level.txt
pydatavolley-2.2.9.dist-info/RECORD
