Metadata-Version: 2.1
Name: pydatavolley
Version: 2.2.9
Summary: A python set of code for reading volleyball scouting files in DataVolley format (*.dvw)
Home-page: https://github.com/openvolley/pydatavolley
Author: ['Tyler Widdison', 'Maurizio Napolitano']
License: MIT
Requires-Dist: numpy >=1.23.3
Requires-Dist: pandas >=1.5.0
